characteristic.py
test_characteristic.py
characteristic-14.2.0.dist-info/DESCRIPTION.rst
characteristic-14.2.0.dist-info/METADATA
characteristic-14.2.0.dist-info/metadata.json
characteristic-14.2.0.dist-info/RECORD
characteristic-14.2.0.dist-info/top_level.txt
characteristic-14.2.0.dist-info/WHEEL
